{
	"name": "bronze_sql_detalle_ventas",
	"properties": {
		"linkedServiceName": {
			"referenceName": "sql_dw_producto_cliente",
			"type": "LinkedServiceReference"
		},
		"folder": {
			"name": "BRONZE"
		},
		"annotations": [],
		"type": "AzureSqlTable",
		"schema": [
			{
				"name": "numorder",
				"type": "varchar"
			},
			{
				"name": "productkey",
				"type": "varchar"
			},
			{
				"name": "custid",
				"type": "varchar"
			},
			{
				"name": "orderdt",
				"type": "varchar"
			},
			{
				"name": "shipdt",
				"type": "varchar"
			},
			{
				"name": "sales",
				"type": "varchar"
			},
			{
				"name": "quantity",
				"type": "varchar"
			},
			{
				"name": "price",
				"type": "varchar"
			}
		],
		"typeProperties": {
			"schema": "BRONZE",
			"table": "DETALLE_VENTAS"
		}
	}
}